{
	"showall": true,
	"greeting": "Neil",
	"pagegap": 1,
	"pagewidth": 1600,
	"time": true,
	"main": true,
	"dateformat": "eu",
	"background_blur": 0,
	"background_bright": 0.5,
	"background_type": "unsplash",
	"quicklinks": true,
	"css": "/* Change weather text here */\n\n#interface #current::after {\n content: 'C on Earth.'\n}\n\n/* the rest */\n\n#interface { color: #dfe1cc!important }\n#interface #time #date { margin: 0 50px }\n#interface #clock-wrapper {\n display: flex;\n align-items: center;\n flex-wrap: wrap;\n\tgap: 1em;\n}\n\n#interface .clock-date {\n\tdisplay: flex;\n}\n\n#show-settings button img {\n filter: sepia(1)\n}\n\n",
	"hide": {
		"weatherdesc": false,
		"weathericon": true
	},
	"clock": {
		"ampm": false,
		"analog": false,
		"seconds": true,
		"size": 1
	},
	"unsplash": {
		"collection": "858219,136301,235,s9aRSbDoSg8",
		"lastCollec": "user",
		"time": 1706435865689
	},
	"font": {
		"size": "13",
		"family": "Space Mono",
		"system": false,
		"weight": "700",
		"weightlist": ["400", "700"]
	}
}
